nidibot/__init__.py
nidibot/nidibot.py
nidibot/py.typed
nidibot/bots/__init__.py
nidibot/bots/bot_base.py
nidibot/bots/bot_factory.py
nidibot/bots/discord_bot.py
nidibot/bots/telegram_bot.py
nidibot/server_provider/__init__.py
nidibot/server_provider/game_server.py
nidibot/server_provider/nitrado_server_provider.py
nidibot/server_provider/server_provider_base.py
nidibot/server_provider/server_provider_factory.py
nidibot/templates/common/bot_configuration.json
nidibot/templates/common/start_bot.py
nidibot/templates/linux/nidibot.service
nidibot-1.2.1.dist-info/LICENSE
nidibot-1.2.1.dist-info/METADATA
nidibot-1.2.1.dist-info/WHEEL
nidibot-1.2.1.dist-info/top_level.txt
nidibot-1.2.1.dist-info/zip-safe
nidibot-1.2.1.dist-info/RECORD
