Metadata-Version: 2.1
Name: nidibot
Version: 1.2.1
Summary: Simple to install and configure bot for controlling your game servers from any messaging platform.
Home-page: https://github.com/morwy/nidibot
Author: Pavel Ivanov
Author-email: 
License: BSD-3-Clause
Project-URL: Bug Tracker, https://github.com/morwy/nidibot/issues
Project-URL: Source Code, https://github.com/morwy/nidibot
Keywords: discord,nitrado,bot
Platform: any
Classifier: Development Status :: 5 - Production/Stable
Classifier: Environment :: Web Environment
Classifier: Intended Audience :: Developers
Classifier: Intended Audience :: System Administrators
Classifier: License :: OSI Approved :: BSD License
Classifier: Operating System :: OS Independent
Classifier: Programming Language :: Python
Classifier: Topic :: Internet :: WWW/HTTP
Classifier: Topic :: Communications :: Chat
Classifier: Topic :: Software Development :: Libraries :: Python Modules
Classifier: Programming Language :: Python :: 3 :: Only
Classifier: Programming Language :: Python :: 3.8
Classifier: Programming Language :: Python :: 3.9
Classifier: Programming Language :: Python :: 3.10
Classifier: Programming Language :: Python :: 3.11
Classifier: Programming Language :: Python :: 3.12
Requires-Python: <3.13,>=3.8.0
License-File: LICENSE
Requires-Dist: dacite
Requires-Dist: ftputil
Requires-Dist: hikari
Requires-Dist: hikari-lightbulb
Requires-Dist: nest-asyncio
Requires-Dist: paramiko
Requires-Dist: python-telegram-bot
Requires-Dist: python-telegram-bot[job-queue]
Requires-Dist: requests
Provides-Extra: test
Requires-Dist: pytest ; extra == 'test'
